LICENSE
MANIFEST.in
README.md
setup.cfg
setup.py
douyu/__init__.py
douyu/chat/__init__.py
douyu/chat/room.py
douyu/chat/network/__init__.py
douyu/chat/network/client.py
douyu/chat/network/message.py
douyu/chat/network/packet.py
douyu/chat/network/utils.py
fitz_douyu.egg-info/PKG-INFO
fitz_douyu.egg-info/SOURCES.txt
fitz_douyu.egg-info/dependency_links.txt
fitz_douyu.egg-info/top_level.txt