Metadata-Version: 1.1
Name: fitz-douyu
Version: 0.0.1
Summary: Python Wrapper for DouyuTV APIs, including support for accessing ChatRoom, e.g. DanMu
Home-page: https://github.com/caojunkai/douyu
Author: Junkai Cao
Author-email: caojunkaiv@gmail.com
License: UNKNOWN
Download-URL: https://github.com/douyu
Keywords: douyu,douyutv,danmu,chat
Platform: UNKNOWN
